mzrewards/__init__.py
mzrewards-0.0.1.dist-info/LICENCE.txt
mzrewards-0.0.1.dist-info/METADATA
mzrewards-0.0.1.dist-info/WHEEL
mzrewards-0.0.1.dist-info/top_level.txt
mzrewards-0.0.1.dist-info/RECORD
